wildflow/__init__.py
wildflow/splat/__init__.py
wildflow/splat/_core.pypy311-pp73-arm-linux-gnu.so
wildflow/splat/ortho.py
wildflow/splat/ortho_renderer.js
wildflow_splat-0.1.7.dist-info/METADATA
wildflow_splat-0.1.7.dist-info/WHEEL
wildflow_splat-0.1.7.dist-info/licenses/LICENSE
wildflow_splat-0.1.7.dist-info/RECORD
