Metadata-Version: 2.4
Name: wildflow-splat
Version: 0.1.7
Classifier: Development Status :: 4 - Beta
Classifier: Intended Audience :: Developers
Classifier: Intended Audience :: Science/Research
Classifier: License :: OSI Approved :: MIT License
Classifier: Programming Language :: Python :: 3
Classifier: Programming Language :: Python :: 3.8
Classifier: Programming Language :: Python :: 3.9
Classifier: Programming Language :: Python :: 3.10
Classifier: Programming Language :: Python :: 3.11
Classifier: Programming Language :: Python :: 3.12
Classifier: Programming Language :: Rust
Classifier: Topic :: Scientific/Engineering
Classifier: Topic :: Multimedia :: Graphics :: 3D Modeling
Classifier: Topic :: Software Development :: Libraries :: Python Modules
Requires-Dist: numpy
Requires-Dist: pillow
Requires-Dist: playwright
Requires-Dist: requests
Requires-Dist: tqdm
Requires-Dist: maturin>=1.0 ; extra == 'dev'
Requires-Dist: pytest>=7.0 ; extra == 'dev'
Provides-Extra: dev
License-File: LICENSE
Summary: PLY point cloud processing for 3D Gaussian splatting workflows
Keywords: ply,point-cloud,3d-gaussian-splatting,colmap,photogrammetry,computer-vision
Author-email: Wildflow AI <info@wildflow.ai>
License: MIT
Requires-Python: >=3.8
Project-URL: repository, https://github.com/wildflowai/wildflow-splat
Project-URL: documentation, https://docs.wildflow.ai
